pbt/__init__.py
pbt/process.py
pbt/prophecy_build_tool.py
prophecy_build_tool_test-1.0.8.dist-info/LICENSE
prophecy_build_tool_test-1.0.8.dist-info/METADATA
prophecy_build_tool_test-1.0.8.dist-info/WHEEL
prophecy_build_tool_test-1.0.8.dist-info/entry_points.txt
prophecy_build_tool_test-1.0.8.dist-info/top_level.txt
prophecy_build_tool_test-1.0.8.dist-info/RECORD
