Metadata-Version: 2.1
Name: prophecy-build-tool-test
Version: 1.0.8
Summary: Prophecy-build-tool (PBT) provides utilities to build and distribute projects created from the Prophecy IDE.
Home-page: https://github.com/SimpleDataLabsInc/prophecy-build-tool
Author: Prophecy
Author-email: maciej@prophecy.io
Project-URL: Bug Tracker, https://github.com/SimpleDataLabsInc/prophecy-build-tool/issues
Classifier: Programming Language :: Python :: 3
Classifier: License :: OSI Approved :: MIT License
Classifier: Operating System :: OS Independent
Requires-Python: >=3.7
License-File: LICENSE
Requires-Dist: requests (>=2.28.0)
Requires-Dist: PyYAML (>=6.0)
Requires-Dist: databricks-cli (>=0.17.1)
Requires-Dist: rich (>=12.5.1)
Requires-Dist: wheel
Requires-Dist: build
